{
  "_meta": {
    "models": {
      "invoices": "Billing documents generated at session end with itemized breakdown of session costs and inventory consumptions.",
      "lineItems": "Individual charges on an invoice including session fees and inventory items.",
      "payments": "Payment records for an invoice, supporting partial payments."
    },
    "relationships": [
      "Each Invoice belongs to one Customer",
      "Each Invoice may be linked to one Session",
      "Each Invoice has many LineItems (session cost + inventory items)",
      "Each Invoice has many Payments (supporting partial payments)"
    ]
  },
  "invoices": [
    {
      "id": "inv-001",
      "invoiceNumber": "INV-0001",
      "customerId": "cust-002",
      "customerName": "Sara Mohamed",
      "customerPhone": "01123456789",
      "sessionId": "sess-100",
      "amount": 110.00,
      "discount": 0,
      "total": 110.00,
      "paidAmount": 110.00,
      "status": "paid",
      "dueDate": "2026-01-13",
      "paidDate": "2026-01-06",
      "createdAt": "2026-01-06T12:00:00Z",
      "lineItems": [
        { "description": "Session - Seat A1 (3 hours)", "quantity": 1, "rate": 75.00, "amount": 75.00 },
        { "description": "Coffee", "quantity": 2, "rate": 15.00, "amount": 30.00 },
        { "description": "Chips (Cheese)", "quantity": 1, "rate": 10.00, "amount": 10.00 }
      ],
      "payments": [
        { "id": "pay-001", "amount": 110.00, "method": "cash", "date": "2026-01-06", "notes": "" }
      ]
    },
    {
      "id": "inv-002",
      "invoiceNumber": "INV-0002",
      "customerId": "cust-004",
      "customerName": "Fatma Ibrahim",
      "customerPhone": "01098765432",
      "sessionId": "sess-101",
      "amount": 45.00,
      "discount": 0,
      "total": 45.00,
      "paidAmount": 45.00,
      "status": "paid",
      "dueDate": "2026-01-12",
      "paidDate": "2026-01-05",
      "createdAt": "2026-01-05T16:00:00Z",
      "lineItems": [
        { "description": "Session - Private Desk 1 (6 hours)", "quantity": 1, "rate": 0, "amount": 0 },
        { "description": "Tea", "quantity": 3, "rate": 10.00, "amount": 30.00 },
        { "description": "Sandwich", "quantity": 1, "rate": 25.00, "amount": 25.00 }
      ],
      "payments": [
        { "id": "pay-002", "amount": 45.00, "method": "card", "date": "2026-01-05", "notes": "Visa ending 4242" }
      ]
    },
    {
      "id": "inv-003",
      "invoiceNumber": "INV-0003",
      "customerId": "cust-006",
      "customerName": "Nour El-Din",
      "customerPhone": "01267890123",
      "sessionId": "sess-102",
      "amount": 75.00,
      "discount": 0,
      "total": 75.00,
      "paidAmount": 0,
      "status": "unpaid",
      "dueDate": "2026-01-12",
      "paidDate": null,
      "createdAt": "2026-01-05T16:00:00Z",
      "lineItems": [
        { "description": "Session - Seat A3 (3 hours)", "quantity": 1, "rate": 75.00, "amount": 75.00 }
      ],
      "payments": []
    },
    {
      "id": "inv-004",
      "invoiceNumber": "INV-0004",
      "customerId": "cust-003",
      "customerName": "Mohamed Ali",
      "customerPhone": "01234567890",
      "sessionId": null,
      "amount": 200.00,
      "discount": 20.00,
      "total": 180.00,
      "paidAmount": 100.00,
      "status": "pending",
      "dueDate": "2026-01-10",
      "paidDate": null,
      "createdAt": "2026-01-04T14:00:00Z",
      "lineItems": [
        { "description": "Weekly Subscription", "quantity": 1, "rate": 200.00, "amount": 200.00 }
      ],
      "payments": [
        { "id": "pay-003", "amount": 100.00, "method": "cash", "date": "2026-01-04", "notes": "Partial payment" }
      ]
    }
  ],
  "paymentMethods": ["cash", "card", "transfer"],
  "invoiceStatuses": ["paid", "unpaid", "pending"]
}
